{"dir":"partners/tree-climbing-italia","locale":"it","body":"\n<EntryInfo variant=\"web\" label=\"Visita\" value=\"[treeclimbing.it](https://treeclimbing.it/)\"/>\n<EntryInfo variant=\"facebook\" label=\"Pagina facebook\" value=\"[facebook.com/TreeClimbingItalia](https://www.facebook.com/TreeClimbingItalia/)\"/>\n\n>“Per insegnare non basta essere un bravo climber. È necessario capire le esigenze e le difficoltà di ogni allievo. In più, visto che siamo appesi a venti metri d’altezza, è importante trasmettere fiducia ed aiutare ognuno a vincere le proprie paure.” _Sergio Ghivelder, dal sito [treeclimbing.it](https://treeclimbing.it/chi-siamo/)_\n\n<Row>\n<Col md={7}>\n\nL’associazione (A. S. D.) **Tree Climbing Italia** – Arbor Training fino al 2010 – è stata fondata nel 2011 da Sergio Ghivelder. Il suo obiettivo era quello di dare vita ad un centro di formazione altamente specializzato nella formazione di climbers e istruttori di Tree Climbing, oltre che avvicinare il pubblico in generale a questa disciplina che è sia una pratica ricreativa di arrampicata, che una tecnica impiegata da arboricoltori professionisti.\n\n</Col>\n<Col md={5}>\n<Alert>\n\nConosciuti all'Agrifest di Varese del 2019, oggi il [parco, gli alberi](/spaces/parco) e la struttura de LaSchola ospitano alcuni dei corsi di Tree Climbing Italia.\n\n</Alert>\n</Col>\n</Row>\n","excerpt":"L’associazione  Tree Climbing Italia – Arbor Training fino al 2010 – è stata fondata nel 2011 da Sergio Ghivelder. Il suo obiettivo era quello di dare vita ad u...","data":{"template":"partners-single","identifier":"tree-climbing-italia","order":6,"website":"https://treeclimbing.it/","name":"Tree Climbing Italia","logo":"https://raw.githubusercontent.com///main/partners/tree-climbing-italia/logo.png","cover":{"image":"https://raw.githubusercontent.com///main/partners/tree-climbing-italia/cover.jpg"}},"id":"partners/tree-climbing-italia","templateSlug":"partners/tree-climbing-italia","slug":"tree-climbing-italia","url":"/partners/tree-climbing-italia"}